temod_open_api/__init__.py
temod_open_api/api.py
temod_open_api/endpoint.py
temod_open_api/exceptions.py
temod_open_api/parser.py
temod_open_api/response.py
temod_open_api-1.0.0.dist-info/LICENSE.txt
temod_open_api-1.0.0.dist-info/METADATA
temod_open_api-1.0.0.dist-info/WHEEL
temod_open_api-1.0.0.dist-info/top_level.txt
temod_open_api-1.0.0.dist-info/RECORD
